mindspore/.commit_id
mindspore/__init__.py
mindspore/_c_dataengine.cpython-37m-x86_64-linux-gnu.so
mindspore/_c_expression.cpython-37m-x86_64-linux-gnu.so
mindspore/_c_mindrecord.cpython-37m-x86_64-linux-gnu.so
mindspore/_checkparam.py
mindspore/_mindspore_offline_debug.cpython-37m-x86_64-linux-gnu.so
mindspore/context.py
mindspore/default_config.py
mindspore/log.py
mindspore/version.py
mindspore/_extends/__init__.py
mindspore/_extends/builtin_operations.py
mindspore/_extends/utils.py
mindspore/_extends/graph_kernel/__init__.py
mindspore/_extends/graph_kernel/expander.py
mindspore/_extends/graph_kernel/parallel_estimate.py
mindspore/_extends/graph_kernel/splitter.py
mindspore/_extends/graph_kernel/utils.py
mindspore/_extends/graph_kernel/expanders/__init__.py
mindspore/_extends/graph_kernel/expanders/_utils.py
mindspore/_extends/graph_kernel/expanders/addn.py
mindspore/_extends/graph_kernel/expanders/assign_add.py
mindspore/_extends/graph_kernel/expanders/batchnorm.py
mindspore/_extends/graph_kernel/expanders/batchnorm_grad.py
mindspore/_extends/graph_kernel/expanders/bias_add_grad.py
mindspore/_extends/graph_kernel/expanders/clip_by_norm_no_div_sum.py
mindspore/_extends/graph_kernel/expanders/conv2d.py
mindspore/_extends/graph_kernel/expanders/dropout_grad.py
mindspore/_extends/graph_kernel/expanders/equal_count.py
mindspore/_extends/graph_kernel/expanders/erfc.py
mindspore/_extends/graph_kernel/expanders/expand_dims.py
mindspore/_extends/graph_kernel/expanders/fused_adam.py
mindspore/_extends/graph_kernel/expanders/fused_adam_weight_decay.py
mindspore/_extends/graph_kernel/expanders/fused_mul_add.py
mindspore/_extends/graph_kernel/expanders/gather.py
mindspore/_extends/graph_kernel/expanders/gelu.py
mindspore/_extends/graph_kernel/expanders/gelu_grad.py
mindspore/_extends/graph_kernel/expanders/gkdropout.py
mindspore/_extends/graph_kernel/expanders/identity.py
mindspore/_extends/graph_kernel/expanders/lamb_apply_optimizer_assign.py
mindspore_ascend_dev-0.0.1.dev20211115.dist-info/METADATA
mindspore_ascend_dev-0.0.1.dev20211115.dist-info/WHEEL
mindspore_ascend_dev-0.0.1.dev20211115.dist-info/entry_points.txt
mindspore_ascend_dev-0.0.1.dev20211115.dist-info/top_level.txt
mindspore_ascend_dev-0.0.1.dev20211115.dist-info/RECORD
